{
  "required": true,
  "package": "net.midget807.afmweapons.mixin.client",
  "compatibilityLevel": "JAVA_17",
  "client": [
    "BackgroundRendererMixin",
    "BipedEntityModelMixin",
    "ClientPlayerEntityMixin",
    "CrossbowPosingMixin",
    "GameRendererMixin",
    "HeldItemFeatureRendererMixin",
    "HeldItemRendererMixin",
    "InGameHudMixin",
    "ItemRendererAccessor",
    "ItemRendererMixin",
    "LightmapTextureManagerMixin",
    "ModelLoaderMixin",
    "TooltipComponentMixin",
    "WorldRendererMixin"
  ],
  "injectors": {
    "defaultRequire": 1
  },
  "mixins": [
    "PlayerEntityRendererMixin"
  ]
}